git_diff_days/__init__.py
git_diff_days/cli.py
git_diff_days-0.1.0.dist-info/METADATA
git_diff_days-0.1.0.dist-info/WHEEL
git_diff_days-0.1.0.dist-info/entry_points.txt
git_diff_days-0.1.0.dist-info/top_level.txt
git_diff_days-0.1.0.dist-info/RECORD
